opencood/__init__.py
opencood/cood.py
opencood/version.py
opencood/data_utils/__init__.py
opencood/data_utils/augmentor/__init__.py
opencood/data_utils/augmentor/augment_utils.py
opencood/data_utils/augmentor/data_augmentor.py
opencood/data_utils/datasets/__init__.py
opencood/data_utils/datasets/basedataset.py
opencood/data_utils/datasets/early_fusion_dataset.py
opencood/data_utils/datasets/early_fusion_vis_dataset.py
opencood/data_utils/datasets/intermediate_fusion_dataset.py
opencood/data_utils/datasets/late_fusion_dataset.py
opencood/data_utils/post_processor/__init__.py
opencood/data_utils/post_processor/base_postprocessor.py
opencood/data_utils/post_processor/bev_postprocessor.py
opencood/data_utils/post_processor/voxel_postprocessor.py
opencood/data_utils/pre_processor/__init__.py
opencood/data_utils/pre_processor/base_preprocessor.py
opencood/data_utils/pre_processor/bev_preprocessor.py
opencood/data_utils/pre_processor/sp_voxel_preprocessor.py
opencood/data_utils/pre_processor/voxel_preprocessor.py
opencood/hypes_yaml/__init__.py
opencood/hypes_yaml/download_yaml.py
opencood/hypes_yaml/pixor_early_fusion.yaml
opencood/hypes_yaml/pixor_intermediate_fusion.yaml
opencood/hypes_yaml/pixor_late_fusion.yaml
opencood/hypes_yaml/point_pillar_early_fusion.yaml
opencood/hypes_yaml/point_pillar_fcooper.yaml
opencood/hypes_yaml/point_pillar_intermediate_fusion.yaml
opencood/hypes_yaml/point_pillar_late_fusion.yaml
opencood/hypes_yaml/point_pillar_v2vnet.yaml
opencood/hypes_yaml/second_early_fusion.yaml
opencood/hypes_yaml/second_intermediate_fusion.yaml
opencood/hypes_yaml/second_late_fusion.yaml
opencood/hypes_yaml/visualization.yaml
opencood/hypes_yaml/voxelnet_early_fusion.yaml
opencood/hypes_yaml/voxelnet_intermediate_fusion.yaml
opencood/hypes_yaml/voxelnet_late_fusion.yaml
opencood/hypes_yaml/yaml_utils.py
opencood/loss/__init__.py
opencood/loss/pixor_loss.py
opencood/loss/point_pillar_loss.py
opencood/loss/voxel_net_loss.py
opencood/model_dir/__init__.py
opencoodx-0.1.19.dist-info/LICENSE
opencoodx-0.1.19.dist-info/METADATA
opencoodx-0.1.19.dist-info/WHEEL
opencoodx-0.1.19.dist-info/entry_points.txt
opencoodx-0.1.19.dist-info/top_level.txt
opencoodx-0.1.19.dist-info/RECORD
