Metadata-Version: 2.1
Name: opencoodx
Version: 0.1.19
Summary: An opensource pytorch framework for autonomous driving cooperative detection
Home-page: https://github.com/ucla-mobility/OpenCDA.git
Author: Runsheng Xu, Hao Xiang, Zhaoliang Zheng
Author-email: rxx3386@ucla.edu,haxiang@g.ucla.edu,zhz03@g.ucla.edu
License: MIT
Classifier: Topic :: Software Development :: Libraries :: Python Modules
Classifier: Programming Language :: Python
Classifier: Programming Language :: Python :: 3.7
Classifier: Programming Language :: Python :: 3.8
License-File: LICENSE
Requires-Dist: matplotlib
Requires-Dist: numpy
Requires-Dist: open3d
Requires-Dist: opencv-python
Requires-Dist: cython
Requires-Dist: tensorboardX
Requires-Dist: shapely
Requires-Dist: einops
Requires-Dist: easydict
Requires-Dist: gdown
